LAB2/lab2.v
//以前者(1ns)為單位，以後者(1ps)的時間，查看一次電路的行為
`timescale 1ns/1ps

//宣告module名稱,輸出入名稱
module lab(
	CLK, 
	RST, 
	in_a, 
	in_b, 
	Product, 
	Product_Valid
);
// in_a * in_b = Product
// in_a is Multiplicand , in_b is Multiplier
					
//定義port, 包含input, output
input 			CLK, RST;		//沒有寫[15:0] 是線 沒有暫存功能
input 	[15:0]	in_a;			// Multiplicand
input 	[15:0]	in_b;			// Multiplier
output 	[31:0]  Product;
output  		Product_Valid;

reg 	[31:0]	Mplicand;		//被乘數
reg 	[15:0]	Mplier;			//乘數
reg 	[31:0]	Product;
reg 			Product_Valid;
reg 	[5:0]	Counter ;
reg				sign;			//正負號判斷 (signed)

//Counter
always @(posedge CLK or posedge RST)  //always  類似while 後面成立就跑  不同always會同時跑  posedge 0到1 nagadge 1到0
begin
	if(RST)//if RST is 1 
		Counter <= 6'b0;
	else
		Counter <= Counter + 6'b1;

end

//Product
always @(posedge CLK or posedge RST)
begin
	//初始化數值
	if(RST) begin
		Product  <= 31'b0;
		Mplicand <= 31'b0;
		Mplier   <= 16'b0;
		/*
			正負號判斷
			write your code here
		*/
		sign <= (in_a[15]) ^ (in_b[15]);
		

	end 
	//輸入乘數與被乘數
	else if(Counter == 6'd0) begin  // 6代表6bit 'd代表10進位  0代表前面補0 故寫6'd9 = 001001
		Product	 	<= 31'b0; //b是2進位
		//乘數與被乘數皆為正數

		/*
			被乘數為負數(in_a)
			乘數為負數(in_b)
			乘數與被乘數皆為負數
			write your code here
		*/

		if ((in_b[15] == 1) && (in_a[15] == 0) )begin
			Mplicand 	<= {16'b0,in_a}; 
			Mplier 		<= ~in_b + 1'b1; //補數+1
		end
		else if ( (in_b[15] == 0) && (in_a[15] == 1) )begin
			Mplicand 	<= {16'b0,~in_a + 1'b1} ;//補數+1		
			Mplier	 	<= in_b;
		end
		else if ( (in_b[15] == 1) && (in_a[15] == 1) ) begin
			Mplicand 	<= {16'b0,~in_a + 1'b1};//補數+1	
			Mplier	    <= ~in_b + 1'b1; //補數+1
		end
		else begin
			Mplicand 	<= {16'b0,in_a}; // 高位補0 低位放in_a
			Mplier	 	<= in_b;
		end

	
		
		
	end 
	//乘法與數值移位
	else if(Counter <=6'd16) //位移16位元內都要做
	begin
		if(Mplier[0] == 1'b1) 	
			Product 	<= Mplicand + Product;
		
		//利用sign來判斷結果(Product)是否需要二補數轉換
		//write your code here	

	
		Mplicand 	<= Mplicand << 1'b1; //往左shf一位
		Mplier 		<= Mplier >> 1'b1; // //往右shf一位
		

		
	end 
	else begin
		if (sign == 1'b1 ) 
			Product <= ~(Product-1'b1)  ;
		else 
			Product <= Product  ;
			
		Mplicand	<= Mplicand;
		Mplier 		<= Mplier;
	end
end

//Product_Valid
always @(posedge CLK or posedge RST)
begin
	if(RST)
		Product_Valid <=1'b0;
	else if(Counter==6'd17)
		Product_Valid <=1'b1;
	else
		Product_Valid <=1'b0;
end

endmodule

LAB2/lab2_mulv1_tb.v
`timescale 1ns/1ps
`include "lab2.v"  //編譯 

//`define SEED 120
module tb_lab2();


reg signed  [15:0]	in_a;
reg signed  [15:0]	in_b;
reg 				CLK;
reg					reset;

wire signed [31:0]	out;
wire 				out_valid;
reg 		[5:0]	count;
reg signed 	[31:0]	correct_ans;
reg 				error;
//integer seed;

reg signed 	[15:0]	temp_a;
reg signed 	[15:0]	temp_b;


lab m1(CLK, reset, in_a, in_b, out, out_valid);

initial begin //拉好線 

	$dumpfile("lab2.vcd");  // gtkwave
	$dumpvars;
	CLK = 1'b0;
	#20 reset = 1;
		temp_a = 16'd3;
		temp_b = 16'd9;
	#20 reset = 0;


	#700 reset = 1;
		temp_a = 16'd1111;
		temp_b = 16'd1001;
	#20 reset = 0;


	#700 reset = 1;
		temp_a = -16'd10;
		temp_b = 16'd14;
	#20 reset = 0;

	#700 reset = 1;
		temp_a = 16'd123;
		temp_b = -16'd7;
	#20 reset = 0;

	#700 reset = 1;
		temp_a = -16'd1;
		temp_b = -16'd60;
	#20 reset = 0;


	#20 reset = 0;
	#700 $finish;


end

always #10 CLK = ~CLK;  //10ms 10^-9  CLK 會相反

	always @(posedge CLK or posedge reset)
	begin
		if(reset)
		begin
			count <= 0;
			in_a <= temp_a;
			in_b <= temp_b;
			correct_ans <= 0;
			error <= 0;
		end

		else
		begin
			correct_ans <= in_a * in_b;
			count <= count +1;

			if(out_valid==1)
				if(out != correct_ans)
				begin
					error <=1;
					$display ();
					$display ("//////////");
					$display ("// Fail //");
					$display ("//////////");
					$display ("doing %d * %d ...\n",temp_a, temp_b);
					$display ("your answer is %d,\nbut correct answer is %d\n",
					out, correct_ans);
					$display ();
				end
				else
				begin
					error <= 0;
					$display ();
					$display ("////////////////");
					$display ("// Successful //");
					$display ("////////////////");
					$display ("doing %d * %d ...\n",temp_a, temp_b);
					$display ("your answer is %d,\ncorrect answer is %d\n",
					out, correct_ans);
					$display ();
				end
		end
	end

endmodule

LAB2/lab2.vcd
$date
	Fri Oct 25 15:49:14 2019
$end
$version
	Icarus Verilog
$end
$timescale
	1ps
$end
$scope module tb_lab2 $end
$var wire 32 ! out [31:0] $end
$var wire 1 " out_valid $end
$var reg 1 # CLK $end
$var reg 32 $ correct_ans [31:0] $end
$var reg 6 % count [5:0] $end
$var reg 1 & error $end
$var reg 16 ' in_a [15:0] $end
$var reg 16 ( in_b [15:0] $end
$var reg 1 ) reset $end
$var reg 16 * temp_a [15:0] $end
$var reg 16 + temp_b [15:0] $end
$scope module m1 $end
$var wire 1 , CLK $end
$var wire 1 - RST $end
$var wire 16 . in_a [15:0] $end
$var wire 16 / in_b [15:0] $end
$var reg 6 0 Counter [5:0] $end
$var reg 32 1 Mplicand [31:0] $end
$var reg 16 2 Mplier [15:0] $end
$var reg 32 3 Product [31:0] $end
$var reg 1 4 Product_Valid $end
$var reg 1 5 sign $end
$upscope $end
$upscope $end
$enddefinitions $end
#0
$dumpvars
x5
x4
bx 3
bx 2
bx 1
bx 0
bx /
bx .
x-
0,
bx +
bx *
x)
bx (
bx '
x&
bx %
bx $
0#
x"
bx !
$end
#10000
04
0"
1#
1,
#20000
0&
b0 $
b1001 (
b1001 /
b11 '
b11 .
b0 %
b0 2
b0 1
b0 3
b0 !
b0 0
0#
0,
b1001 +
b11 *
1)
1-
#30000
05
1#
1,
#40000
0#
0,
0)
0-
#50000
b1 %
b11011 $
b1001 2
b11 1
b1 0
1#
1,
#60000
0#
0,
#70000
b10 0
b100 2
b110 1
b11 3
b11 !
b10 %
1#
1,
#80000
0#
0,
#90000
b11 %
b10 2
b1100 1
b11 0
1#
1,
#100000
0#
0,
#110000
b100 0
b1 2
b11000 1
b100 %
1#
1,
#120000
0#
0,
#130000
b101 %
b0 2
b110000 1
b11011 3
b11011 !
b101 0
1#
1,
#140000
0#
0,
#150000
b110 0
b1100000 1
b110 %
1#
1,
#160000
0#
0,
#170000
b111 %
b11000000 1
b111 0
1#
1,
#180000
0#
0,
#190000
b1000 0
b110000000 1
b1000 %
1#
1,
#200000
0#
0,
#210000
b1001 %
b1100000000 1
b1001 0
1#
1,
#220000
0#
0,
#230000
b1010 0
b11000000000 1
b1010 %
1#
1,
#240000
0#
0,
#250000
b1011 %
b110000000000 1
b1011 0
1#
1,
#260000
0#
0,
#270000
b1100 0
b1100000000000 1
b1100 %
1#
1,
#280000
0#
0,
#290000
b1101 %
b11000000000000 1
b1101 0
1#
1,
#300000
0#
0,
#310000
b1110 0
b110000000000000 1
b1110 %
1#
1,
#320000
0#
0,
#330000
b1111 %
b1100000000000000 1
b1111 0
1#
1,
#340000
0#
0,
#350000
b10000 0
b11000000000000000 1
b10000 %
1#
1,
#360000
0#
0,
#370000
b10001 %
b110000000000000000 1
b10001 0
1#
1,
#380000
0#
0,
#390000
b10010 0
14
1"
b10010 %
1#
1,
#400000
0#
0,
#410000
b10011 %
04
0"
b10011 0
1#
1,
#420000
0#
0,
#430000
b10100 0
b10100 %
1#
1,
#440000
0#
0,
#450000
b10101 %
b10101 0
1#
1,
#460000
0#
0,
#470000
b10110 0
b10110 %
1#
1,
#480000
0#
0,
#490000
b10111 %
b10111 0
1#
1,
#500000
0#
0,
#510000
b11000 0
b11000 %
1#
1,
#520000
0#
0,
#530000
b11001 %
b11001 0
1#
1,
#540000
0#
0,
#550000
b11010 0
b11010 %
1#
1,
#560000
0#
0,
#570000
b11011 %
b11011 0
1#
1,
#580000
0#
0,
#590000
b11100 0
b11100 %
1#
1,
#600000
0#
0,
#610000
b11101 %
b11101 0
1#
1,
#620000
0#
0,
#630000
b11110 0
b11110 %
1#
1,
#640000
0#
0,
#650000
b11111 %
b11111 0
1#
1,
#660000
0#
0,
#670000
b100000 0
b100000 %
1#
1,
#680000
0#
0,
#690000
b100001 %
b100001 0
1#
1,
#700000
0#
0,
#710000
b100010 0
b100010 %
1#
1,
#720000
0#
0,
#730000
b100011 %
b100011 0
1#
1,
#740000
b0 0
b0 1
b0 3
b0 !
b0 $
b1111101001 (
b1111101001 /
b10001010111 '
b10001010111 .
b0 %
0#
0,
b1111101001 +
b10001010111 *
1)
1-
#750000
1#
1,
#760000
0#
0,
0)
0-
#770000
b1 0
b1111101001 2
b10001010111 1
b1 %
b100001111100000101111 $
1#
1,
#780000
0#
0,
#790000
b10 %
b111110100 2
b100010101110 1
b10001010111 3
b10001010111 !
b10 0
1#
1,
#800000
0#
0,
#810000
b11 0
b11111010 2
b1000101011100 1
b11 %
1#
1,
#820000
0#
0,
#830000
b100 %
b1111101 2
b10001010111000 1
b100 0
1#
1,
#840000
0#
0,
#850000
b101 0
b111110 2
b100010101110000 1
b10011100001111 3
b10011100001111 !
b101 %
1#
1,
#860000
0#
0,
#870000
b110 %
b11111 2
b1000101011100000 1
b110 0
1#
1,
#880000
0#
0,
#890000
b111 0
b1111 2
b10001010111000000 1
b1011000111101111 3
b1011000111101111 !
b111 %
1#
1,
#900000
0#
0,
#910000
b1000 %
b111 2
b100010101110000000 1
b11100011110101111 3
b11100011110101111 !
b1000 0
1#
1,
#920000
0#
0,
#930000
b1001 0
b11 2
b1000101011100000000 1
b111111001100101111 3
b111111001100101111 !
b1001 %
1#
1,
#940000
0#
0,
#950000
b1010 %
b1 2
b10001010111000000000 1
b10000100101000101111 3
b10000100101000101111 !
b1010 0
1#
1,
#960000
0#
0,
#970000
b1011 0
b0 2
b100010101110000000000 1
b100001111100000101111 3
b100001111100000101111 !
b1011 %
1#
1,
#980000
0#
0,
#990000
b1100 %
b1000101011100000000000 1
b1100 0
1#
1,
#1000000
0#
0,
#1010000
b1101 0
b10001010111000000000000 1
b1101 %
1#
1,
#1020000
0#
0,
#1030000
b1110 %
b100010101110000000000000 1
b1110 0
1#
1,
#1040000
0#
0,
#1050000
b1111 0
b1000101011100000000000000 1
b1111 %
1#
1,
#1060000
0#
0,
#1070000
b10000 %
b10001010111000000000000000 1
b10000 0
1#
1,
#1080000
0#
0,
#1090000
b10001 0
b100010101110000000000000000 1
b10001 %
1#
1,
#1100000
0#
0,
#1110000
b10010 %
14
1"
b10010 0
1#
1,
#1120000
0#
0,
#1130000
b10011 0
04
0"
b10011 %
1#
1,
#1140000
0#
0,
#1150000
b10100 %
b10100 0
1#
1,
#1160000
0#
0,
#1170000
b10101 0
b10101 %
1#
1,
#1180000
0#
0,
#1190000
b10110 %
b10110 0
1#
1,
#1200000
0#
0,
#1210000
b10111 0
b10111 %
1#
1,
#1220000
0#
0,
#1230000
b11000 %
b11000 0
1#
1,
#1240000
0#
0,
#1250000
b11001 0
b11001 %
1#
1,
#1260000
0#
0,
#1270000
b11010 %
b11010 0
1#
1,
#1280000
0#
0,
#1290000
b11011 0
b11011 %
1#
1,
#1300000
0#
0,
#1310000
b11100 %
b11100 0
1#
1,
#1320000
0#
0,
#1330000
b11101 0
b11101 %
1#
1,
#1340000
0#
0,
#1350000
b11110 %
b11110 0
1#
1,
#1360000
0#
0,
#1370000
b11111 0
b11111 %
1#
1,
#1380000
0#
0,
#1390000
b100000 %
b100000 0
1#
1,
#1400000
0#
0,
#1410000
b100001 0
b100001 %
1#
1,
#1420000
0#
0,
#1430000
b100010 %
b100010 0
1#
1,
#1440000
0#
0,
#1450000
b100011 0
b100011 %
1#
1,
#1460000
b0 $
b1110 (
b1110 /
b1111111111110110 '
b1111111111110110 .
b0 %
b0 1
b0 3
b0 !
b0 0
0#
0,
b1110 +
b1111111111110110 *
1)
1-
#1470000
15
1#
1,
#1480000
0#
0,
0)
0-
#1490000
b1 %
b11111111111111111111111101110100 $
b1110 2
b1010 1
b1 0
1#
1,
#1500000
0#
0,
#1510000
b10 0
b111 2
b10100 1
b10 %
1#
1,
#1520000
0#
0,
#1530000
b11 %
b11 2
b101000 1
b10100 3
b10100 !
b11 0
1#
1,
#1540000
0#
0,
#1550000
b100 0
b1 2
b1010000 1
b111100 3
b111100 !
b100 %
1#
1,
#1560000
0#
0,
#1570000
b101 %
b0 2
b10100000 1
b10001100 3
b10001100 !
b101 0
1#
1,
#1580000
0#
0,
#1590000
b110 0
b101000000 1
b110 %
1#
1,
#1600000
0#
0,
#1610000
b111 %
b1010000000 1
b111 0
1#
1,
#1620000
0#
0,
#1630000
b1000 0
b10100000000 1
b1000 %
1#
1,
#1640000
0#
0,
#1650000
b1001 %
b101000000000 1
b1001 0
1#
1,
#1660000
0#
0,
#1670000
b1010 0
b1010000000000 1
b1010 %
1#
1,
#1680000
0#
0,
#1690000
b1011 %
b10100000000000 1
b1011 0
1#
1,
#1700000
0#
0,
#1710000
b1100 0
b101000000000000 1
b1100 %
1#
1,
#1720000
0#
0,
#1730000
b1101 %
b1010000000000000 1
b1101 0
1#
1,
#1740000
0#
0,
#1750000
b1110 0
b10100000000000000 1
b1110 %
1#
1,
#1760000
0#
0,
#1770000
b1111 %
b101000000000000000 1
b1111 0
1#
1,
#1780000
0#
0,
#1790000
b10000 0
b1010000000000000000 1
b10000 %
1#
1,
#1800000
0#
0,
#1810000
b10001 %
b10100000000000000000 1
b10001 0
1#
1,
#1820000
0#
0,
#1830000
b10010 0
b11111111111111111111111101110100 3
b11111111111111111111111101110100 !
14
1"
b10010 %
1#
1,
#1840000
0#
0,
#1850000
b10011 %
04
0"
b10001100 3
b10001100 !
b10011 0
1#
1,
#1860000
0#
0,
#1870000
b10100 0
b11111111111111111111111101110100 3
b11111111111111111111111101110100 !
b10100 %
1#
1,
#1880000
0#
0,
#1890000
b10101 %
b10001100 3
b10001100 !
b10101 0
1#
1,
#1900000
0#
0,
#1910000
b10110 0
b11111111111111111111111101110100 3
b11111111111111111111111101110100 !
b10110 %
1#
1,
#1920000
0#
0,
#1930000
b10111 %
b10001100 3
b10001100 !
b10111 0
1#
1,
#1940000
0#
0,
#1950000
b11000 0
b11111111111111111111111101110100 3
b11111111111111111111111101110100 !
b11000 %
1#
1,
#1960000
0#
0,
#1970000
b11001 %
b10001100 3
b10001100 !
b11001 0
1#
1,
#1980000
0#
0,
#1990000
b11010 0
b11111111111111111111111101110100 3
b11111111111111111111111101110100 !
b11010 %
1#
1,
#2000000
0#
0,
#2010000
b11011 %
b10001100 3
b10001100 !
b11011 0
1#
1,
#2020000
0#
0,
#2030000
b11100 0
b11111111111111111111111101110100 3
b11111111111111111111111101110100 !
b11100 %
1#
1,
#2040000
0#
0,
#2050000
b11101 %
b10001100 3
b10001100 !
b11101 0
1#
1,
#2060000
0#
0,
#2070000
b11110 0
b11111111111111111111111101110100 3
b11111111111111111111111101110100 !
b11110 %
1#
1,
#2080000
0#
0,
#2090000
b11111 %
b10001100 3
b10001100 !
b11111 0
1#
1,
#2100000
0#
0,
#2110000
b100000 0
b11111111111111111111111101110100 3
b11111111111111111111111101110100 !
b100000 %
1#
1,
#2120000
0#
0,
#2130000
b100001 %
b10001100 3
b10001100 !
b100001 0
1#
1,
#2140000
0#
0,
#2150000
b100010 0
b11111111111111111111111101110100 3
b11111111111111111111111101110100 !
b100010 %
1#
1,
#2160000
0#
0,
#2170000
b100011 %
b10001100 3
b10001100 !
b100011 0
1#
1,
#2180000
b0 0
b0 1
b0 3
b0 !
b0 $
b1111111111111001 (
b1111111111111001 /
b1111011 '
b1111011 .
b0 %
0#
0,
b1111111111111001 +
b1111011 *
1)
1-
#2190000
1#
1,
#2200000
0#
0,
0)
0-
#2210000
b1 0
b111 2
b1111011 1
b1 %
b11111111111111111111110010100011 $
1#
1,
#2220000
0#
0,
#2230000
b10 %
b11 2
b11110110 1
b1111011 3
b1111011 !
b10 0
1#
1,
#2240000
0#
0,
#2250000
b11 0
b1 2
b111101100 1
b101110001 3
b101110001 !
b11 %
1#
1,
#2260000
0#
0,
#2270000
b100 %
b0 2
b1111011000 1
b1101011101 3
b1101011101 !
b100 0
1#
1,
#2280000
0#
0,
#2290000
b101 0
b11110110000 1
b101 %
1#
1,
#2300000
0#
0,
#2310000
b110 %
b111101100000 1
b110 0
1#
1,
#2320000
0#
0,
#2330000
b111 0
b1111011000000 1
b111 %
1#
1,
#2340000
0#
0,
#2350000
b1000 %
b11110110000000 1
b1000 0
1#
1,
#2360000
0#
0,
#2370000
b1001 0
b111101100000000 1
b1001 %
1#
1,
#2380000
0#
0,
#2390000
b1010 %
b1111011000000000 1
b1010 0
1#
1,
#2400000
0#
0,
#2410000
b1011 0
b11110110000000000 1
b1011 %
1#
1,
#2420000
0#
0,
#2430000
b1100 %
b111101100000000000 1
b1100 0
1#
1,
#2440000
0#
0,
#2450000
b1101 0
b1111011000000000000 1
b1101 %
1#
1,
#2460000
0#
0,
#2470000
b1110 %
b11110110000000000000 1
b1110 0
1#
1,
#2480000
0#
0,
#2490000
b1111 0
b111101100000000000000 1
b1111 %
1#
1,
#2500000
0#
0,
#2510000
b10000 %
b1111011000000000000000 1
b10000 0
1#
1,
#2520000
0#
0,
#2530000
b10001 0
b11110110000000000000000 1
b10001 %
1#
1,
#2540000
0#
0,
#2550000
b10010 %
14
1"
b11111111111111111111110010100011 3
b11111111111111111111110010100011 !
b10010 0
1#
1,
#2560000
0#
0,
#2570000
b10011 0
b1101011101 3
b1101011101 !
04
0"
b10011 %
1#
1,
#2580000
0#
0,
#2590000
b10100 %
b11111111111111111111110010100011 3
b11111111111111111111110010100011 !
b10100 0
1#
1,
#2600000
0#
0,
#2610000
b10101 0
b1101011101 3
b1101011101 !
b10101 %
1#
1,
#2620000
0#
0,
#2630000
b10110 %
b11111111111111111111110010100011 3
b11111111111111111111110010100011 !
b10110 0
1#
1,
#2640000
0#
0,
#2650000
b10111 0
b1101011101 3
b1101011101 !
b10111 %
1#
1,
#2660000
0#
0,
#2670000
b11000 %
b11111111111111111111110010100011 3
b11111111111111111111110010100011 !
b11000 0
1#
1,
#2680000
0#
0,
#2690000
b11001 0
b1101011101 3
b1101011101 !
b11001 %
1#
1,
#2700000
0#
0,
#2710000
b11010 %
b11111111111111111111110010100011 3
b11111111111111111111110010100011 !
b11010 0
1#
1,
#2720000
0#
0,
#2730000
b11011 0
b1101011101 3
b1101011101 !
b11011 %
1#
1,
#2740000
0#
0,
#2750000
b11100 %
b11111111111111111111110010100011 3
b11111111111111111111110010100011 !
b11100 0
1#
1,
#2760000
0#
0,
#2770000
b11101 0
b1101011101 3
b1101011101 !
b11101 %
1#
1,
#2780000
0#
0,
#2790000
b11110 %
b11111111111111111111110010100011 3
b11111111111111111111110010100011 !
b11110 0
1#
1,
#2800000
0#
0,
#2810000
b11111 0
b1101011101 3
b1101011101 !
b11111 %
1#
1,
#2820000
0#
0,
#2830000
b100000 %
b11111111111111111111110010100011 3
b11111111111111111111110010100011 !
b100000 0
1#
1,
#2840000
0#
0,
#2850000
b100001 0
b1101011101 3
b1101011101 !
b100001 %
1#
1,
#2860000
0#
0,
#2870000
b100010 %
b11111111111111111111110010100011 3
b11111111111111111111110010100011 !
b100010 0
1#
1,
#2880000
0#
0,
#2890000
b100011 0
b1101011101 3
b1101011101 !
b100011 %
1#
1,
#2900000
b0 $
b1111111111000100 (
b1111111111000100 /
b1111111111111111 '
b1111111111111111 .
b0 %
b0 1
b0 3
b0 !
b0 0
0#
0,
b1111111111000100 +
b1111111111111111 *
1)
1-
#2910000
05
1#
1,
#2920000
0#
0,
0)
0-
#2930000
b1 %
b111100 $
b111100 2
b1 1
b1 0
1#
1,
#2940000
0#
0,
#2950000
b10 0
b11110 2
b10 1
b10 %
1#
1,
#2960000
0#
0,
#2970000
b11 %
b1111 2
b100 1
b11 0
1#
1,
#2980000
0#
0,
#2990000
b100 0
b111 2
b1000 1
b100 3
b100 !
b100 %
1#
1,
#3000000
0#
0,
#3010000
b101 %
b11 2
b10000 1
b1100 3
b1100 !
b101 0
1#
1,
#3020000
0#
0,
#3030000
b110 0
b1 2
b100000 1
b11100 3
b11100 !
b110 %
1#
1,
#3040000
0#
0,
#3050000
b111 %
b0 2
b1000000 1
b111100 3
b111100 !
b111 0
1#
1,
#3060000
0#
0,
#3070000
b1000 0
b10000000 1
b1000 %
1#
1,
#3080000
0#
0,
#3090000
b1001 %
b100000000 1
b1001 0
1#
1,
#3100000
0#
0,
#3110000
b1010 0
b1000000000 1
b1010 %
1#
1,
#3120000
0#
0,
#3130000
b1011 %
b10000000000 1
b1011 0
1#
1,
#3140000
0#
0,
#3150000
b1100 0
b100000000000 1
b1100 %
1#
1,
#3160000
0#
0,
#3170000
b1101 %
b1000000000000 1
b1101 0
1#
1,
#3180000
0#
0,
#3190000
b1110 0
b10000000000000 1
b1110 %
1#
1,
#3200000
0#
0,
#3210000
b1111 %
b100000000000000 1
b1111 0
1#
1,
#3220000
0#
0,
#3230000
b10000 0
b1000000000000000 1
b10000 %
1#
1,
#3240000
0#
0,
#3250000
b10001 %
b10000000000000000 1
b10001 0
1#
1,
#3260000
0#
0,
#3270000
b10010 0
14
1"
b10010 %
1#
1,
#3280000
0#
0,
#3290000
b10011 %
04
0"
b10011 0
1#
1,
#3300000
0#
0,
#3310000
b10100 0
b10100 %
1#
1,
#3320000
0#
0,
#3330000
b10101 %
b10101 0
1#
1,
#3340000
0#
0,
#3350000
b10110 0
b10110 %
1#
1,
#3360000
0#
0,
#3370000
b10111 %
b10111 0
1#
1,
#3380000
0#
0,
#3390000
b11000 0
b11000 %
1#
1,
#3400000
0#
0,
#3410000
b11001 %
b11001 0
1#
1,
#3420000
0#
0,
#3430000
b11010 0
b11010 %
1#
1,
#3440000
0#
0,
#3450000
b11011 %
b11011 0
1#
1,
#3460000
0#
0,
#3470000
b11100 0
b11100 %
1#
1,
#3480000
0#
0,
#3490000
b11101 %
b11101 0
1#
1,
#3500000
0#
0,
#3510000
b11110 0
b11110 %
1#
1,
#3520000
0#
0,
#3530000
b11111 %
b11111 0
1#
1,
#3540000
0#
0,
#3550000
b100000 0
b100000 %
1#
1,
#3560000
0#
0,
#3570000
b100001 %
b100001 0
1#
1,
#3580000
0#
0,
#3590000
b100010 0
b100010 %
1#
1,
#3600000
0#
0,
#3610000
b100011 %
b100011 0
1#
1,
#3620000
0#
0,
#3630000
b100100 0
b100100 %
1#
1,
